{
  "kelas": "9",
  "jenis": "Sterofoam",
  "link": [
    {
      "judul": "Bunga hias",
      "link": "https://www.youtube.com/watch?v=HKBQGWfbiEE",
      "bahan": [
        "sterofoam",
        "kawat",
        "lem tembak",
        "tissue",
        "plastic bag",
        "solasi",
        "gunting"
      ],
      "langkah": [
        "Siapkan alat dan bahan yang diperlukan",
        "Bengkokkan ujung kawat di satu sisi",
        "Beri lem tembak secukupnya di bengkokan kawat tersebut",
        "Balut ujung kawat dengan tisu",
        "Bungkus dengan potongan tas plastik, lalu ikat",
        "Rapikan dengan gunting dan korek api",
        "Potong kotak kotak styrofoam 3x3 cm",
        "Bentuk menjadi kelopak bunga, ulangi step hingga didapat jumlah kelopak yang diinginkan",
        "Satukan kelopak bunga tersebut menggunakan lem tembak dengan rapi",
        "Lubangi tengah kumpulan kelopak bunga",
        "Masukkan tangkai kawat yang sudah dibuat tadi"
      ]
    },
    {
      "judul": "Bunga hias sakura",
      "link": "https://www.youtube.com/watch?v=IoHXIlzpUYg",
      "bahan": [
        "sterofoam",
        "koran",
        "kawat",
        "lem tembak",
        "masking tape",
        "cat",
        "tutup botol",
        "mutiara",
        "gunting",
        "cat akrilik"
      ],
      "langkah": [
        "Siapkan alat dan bahan",
        "Gunting koran menjadi beberapa bagian persegi panjang",
        "Potong kawat menjadi tangkai",
        "Balut kawat tersebut dengan koran yang sudah dipotong dan rekatkan dengan lem tembak",
        "Bengkokkan kawat yang sudah dilapisi koran menjadi bentuk tangkai atau ranting pohon, ulangi langkah sampai jumlah ranting yang diinginkan, rekatkan dengan masking tape",
        "Satukan ranting tersebut hingga menjadi pohon berukuran lebih besar, rapikan dengan masking tape dan gunting",
        "Cat bagian batang pohon dengan cat akrilik",
        "Lubangi sterofoam dengan tutup botol hingga mendapat beberapa bagian lingkaran dengan jumlah yang diinginkan",
        "Bentuk styrofoam lingkaran dengan kuku dan gunting sampai menjadi bunga, rapikan",
        "Warnai sedikit dengan krayon",
        "Lubangi tengah bunga dengan pulpen",
        "Tempelkan mutiara kecil di lubang tersebut",
        "Bengkokkan sedikit beberapa kawat yang telah menjadi ranting",
        "Tempelkan bunga sakura menggunakan lem tembak, ulangi hingga ranting penuh"
      ]
    },
    {
      "judul": "Bunga hias",
      "link": "https://www.youtube.com/watch?v=GHbm8B1w6AE",
      "bahan": [
        "sterofoam",
        "kertas hijau",
        "tutup botol",
        "cotton bud",
        "lem tembak",
        "tangkai bunga",
        "gunting",
        "kawat"
      ],
      "langkah": [
        "Siapkan alat dan bahan",
        "Gunting 4 sisi ujung sterofoam, rapikan dengan gunting",
        "Lubangi sterofoam dengan tutup botol hingga didapat 1 lingkaran",
        "Ambil beberapa cotton bud dan gunting dengan diagonal",
        "Rekatkan 4 sisi ujung styrofoam tadi dengan lem tembak hingga berbentuk kelopak bunga",
        "Masukkan cotton bud ke styrofoam yang berbentuk lingkaran, kemudian tempelkan ke bagian tengah (lubang) kelopak bunga",
        "Bentuk kertas hijau menjadi bentuk rumput dan tangkai hijau bunga menggunakan gunting",
        "Lapisi kawat dengan kertas hijau, lalu masukkan ke tangkai bunga yang sudah dibuat"
      ]
    },
    {
      "judul": "Bunga hias",
      "link": "https://www.youtube.com/watch?v=39rzJlKC3xc",
      "bahan": [
        "sterofoam",
        "kawat",
        "kertas hijau",
        "gunting",
        "lem putih",
        "lem tembak",
        "kertas krep",
        "masking tape",
        "spidol warna",
        "roll solasi bekas"
      ],
      "langkah": [
        "Siapkan alat bahan",
        "Potong kawat menjadi beberapa bagian sekitar 5-6 cm",
        "Potong kertas krep hijau sekitar setengah cm",
        "Bungkus kawat dengan kertas krep, rekatkan dengan lem",
        "Gunting styrofoam bagian pinggir berbentuk persegi panjang",
        "Gunting satu sisi styrofoam selebar 1 mm, jangan sampai putus",
        "Lem ujung kawat, gulung styrofoam secara perlahan",
        "Beri warna sesuai selera",
        "Lubangi sterofoam dengan tutup botol untuk mendapatkan bentuk lingkaran",
        "Gunting setiap sisi menjadi 8 bagian untuk membuat motif bunga",
        "Siapkan roll bekas selotip kecil, masukkan secara perlahan motif bunga tersebut",
        "Gunakan lem tembak untuk merapatkan bunga, kemudian lepas dari lubang selotip",
        "Masukkan kawat dengan styrofoam di ujung ke bagian tengah bunga",
        "Ulangi step tersebut hingga didapat banyak tangkai bunga",
        "Ambil beberapa tangkai, rekatkan dengan masking tape hijau",
        "Susun di kawat yang panjang, rapikan dengan masking tape dan gunting"
      ]
    },
    {
      "judul": "Bunga hias lavender",
      "link": "https://www.youtube.com/watch?v=5BNvJ6F1p3o",
      "bahan": [
        "sterofoam",
        "sapu lidi bekas",
        "kawat",
        "gunting",
        "lem tembak",
        "cutter/ gunting",
        "cat semprot"
      ],
      "langkah": [
        "Siapkan alat dan bahan",
        "Tipiskan ujung lidi dengan cutter",
        "Cat dengan cat semprot",
        "Potong styrofoam dengan cutter hingga mendapat bentuk persegi",
        "Gunting membentuk pola bunga",
        "Beri warna sesuai selera",
        "Rekatkan satu kelopak dengan kelopak lain menggunakan lem tembak, ulangi step hingga mendapatkan jumlah yang diinginkan",
        "Masukkan kelopak bunga ke lidi secara berjarak, dan direkatkan dengan lem tembak"
      ]
    },
    {
      "judul": "Bunga hias",
      "link": "https://www.youtube.com/watch?v=ek0vlXL1xKs",
      "bahan": [
        "sterofoam",
        "kawat",
        "gunting",
        "plastik kresek hijau",
        "korek api",
        "lem tembak"
      ],
      "langkah": [
        "Siapkan alat dan bahan",
        "Gunting styrofoam dengan ukuran sekitar 2,5cm x 4 cm, kemudian bentuk menjadi kelopak bunga, rapikan dengan tangan",
        "Ambil plastic kresek hijau, gulung kecil dan rapikan dengan korek api",
        "Tempelkan di ujung kelopak bunga",
        "Potong styrofoam dengan ukuran 2.5 x 2.5 cm, bentuk menjadi oval menggunakan gunting",
        "Tempelkan beberapa kelopak bunga menggunakan lem tembak",
        "Gabungkan 4 lapis kresek hijau dan potong sebesar 1 x 6 cm, lalu gunting bagian satu sisinya jangan sampai putus. Rapikan dengan korek api",
        "Lilitkan ke ujung kawat dan rekatkan dengan lem tembak",
        "Masukkan dan tempel kelopak bunga ke kawat"
      ]
    },
    {
      "judul": "Bunga hias",
      "link": "https://www.youtube.com/watch?v=IhaFeHq3B8s",
      "bahan": [
        "sterofoam",
        "kawat",
        "gunting",
        "tang kecil",
        "lem tembak",
        "cat kuning dan hijau",
        "kuas"
      ],
      "langkah": [
        "Siapkan alat dan bahan",
        "Gunting styrofoam menjadi dua bagian, kemudian gunting 4 ujung sterofoam, rapikan ujungnya hingga membentuk seperti kelopak bunga",
        "Susun kelopak bunga kemudian rekatkan dengan lem tembak",
        "Potong kawat menjadi beberapa bagian",
        "Rangkai kawat dan tekuk ujung kawat dengan tang",
        "Teteskan lem tembak di setiap ujung kawat",
        "Masukkan kawat ke tengah kelopak bunga",
        "Cat kawat dengan warna yang diinginkan",
        "Cat kelopak bunga dengan warna yang diinginkan",
        "Gunting styrofoam membentuk daun, kemudian cat dengan warna hijau"
      ]
    },
    {
      "judul": "Papan Hiasan",
      "link": "https://www.youtube.com/watch?v=XPB_W33iA1g",
      "bahan": [
        "kardus",
        "kertas bungkus nasi",
        "lem putih",
        "spidol",
        "kertas karton",
        "gunting",
        "tusuk sate"
      ],
      "langkah_langkah": [
        "Siapkan alat dan bahan",
        "Sediakan kardus berukuran 34 x 24 cm",
        "Bungkus kardus dengan kertas nasi, rekatkan dengan lem putih",
        "Gunting kertas karton hitam berukuran 33 x 20 cm, gambar batang pohon beserta rantingnya, gunting sesuai bentuk",
        "Lem gambar tersebut ke kardus yang sudah dilapisi kertas nasi",
        "Siapkan 4 tusuk sate dan lapisi dengan karton hitam, gunting runcing ujungnya",
        "Tempelkan 4 tusuk sate yang sudah dilapisi kertas karton mengelilingi kardus hingga membentuk seperti frame/ bingkai",
        "Gunting styrofoam dan bolongi menggunakan tutup botol hingga didapat beberapa lingkaran",
        "Gunting styrofoam lingkaran menjadi 5 bagian, rapikan hingga membentuk kelopak bunga",
        "Tandai dengan pensil di tengah bunga, warnai sesuai selera, ulangi step hingga mendapat jumlah bunga yang diinginkan",
        "Susun bunga yang sudah diwarnai ke kardus menggunakan lem tembak",
        "Tambahkan hiasan sesuai sekreatif mungkin"
      ]
    }
  ]
}
